{
	"FeeIntervals": [
		{
			"fee": 9,
			"start": "06:00",
			"end": "06:30"
		},
		{
			"fee": 9,
			"start": "08:30",
			"end": "15:00"
		},
		{
			"fee": 9,
			"start": "18:00",
			"end": "18:30"
		},
		{
			"fee": 16,
			"start": "06:30",
			"end": "07:00"
		},
		{
			"fee": 16,
			"start": "08:00",
			"end": "08:30"
		},
		{
			"fee": 16,
			"start": "15:00",
			"end": "15:30"
		},
		{
			"fee": 16,
			"start": "17:00",
			"end": "18:00"
		},
		{
			"fee": 22,
			"start": "07:00",
			"end": "08:00"
		},
		{
			"fee": 22,
			"start": "15:30",
			"end": "17:00"
		}
	],

	"VehicleTypes": [
		{
			"Id": 1,
			"TypeName": "MOTORCYCLE",
			"IsTollFree": true
		},
		{
			"Id": 2,
			"TypeName": "TRACTOR",
			"IsTollFree": true
		},
		{
			"Id": 3,
			"TypeName": "EMERGENCY",
			"IsTollFree": true
		},
		{
			"Id": 4,
			"TypeName": "DIPLOMAT",
			"IsTollFree": true
		},
		{
			"Id": 5,
			"TypeName": "FOREIGN",
			"IsTollFree": true
		},
		{
			"Id": 6,
			"TypeName": "MILITARY",
			"IsTollFree": true
		},
		{
			"Id": 7,
			"TypeName": "CAR",
			"IsTollFree": false
		},
		{
			"Id": 8,
			"TypeName": "TRUCK",
			"IsTollFree": false
		},
		{
			"Id": 9,
			"TypeName": "BUS",
			"IsTollFree": false
		}
	],

	"SimulatedVehicleApiDataSeedData": [
		{
			"PlateNumber": "PTP461",
			"OwnerName": "Tommy Tjernqvist",
			"VehicleTypeName": "CAR"
		},
		{
			"PlateNumber": "FJN740",
			"OwnerName": "Hugo Håkman",
			"VehicleTypeName": "CAR"
		},
		{
			"PlateNumber": "ZCX563",
			"OwnerName": "Linda Längström",
			"VehicleTypeName": "CAR"
		},
		{
			"PlateNumber": "VAT087",
			"OwnerName": "Kalle Krantz",
			"VehicleTypeName": "TRUCK"
		},
		{
			"PlateNumber": "CUL352",
			"OwnerName": "Benny Bäckström",
			"VehicleTypeName": "BUS"
		},
		{
			"PlateNumber": "UXL821",
			"OwnerName": "Ronny Röjberg",
			"VehicleTypeName": "CAR"
		},
		{
			"PlateNumber": "MKW921",
			"OwnerName": "Sally Ståhl",
			"VehicleTypeName": "CAR"
		},
		{
			"PlateNumber": "OLU514",
			"OwnerName": "Eddie Elg",
			"VehicleTypeName": "MILITARY"
		},
		{
			"PlateNumber": "TJY229",
			"OwnerName": "Felix Färnelund",
			"VehicleTypeName": "CAR"
		},
		{
			"PlateNumber": "UHA649",
			"OwnerName": "Jörgen Järvstad",
			"VehicleTypeName": "TRUCK"
		},
		{
			"PlateNumber": "BTS372",
			"OwnerName": "Lotta Löfgren",
			"VehicleTypeName": "TRUCK"
		},
		{
			"PlateNumber": "XKL291",
			"OwnerName": "Gustav Gullberg",
			"VehicleTypeName": "CAR"
		},
		{
			"PlateNumber": "PNY183",
			"OwnerName": "Mona Mörk",
			"VehicleTypeName": "CAR"
		},
		{
			"PlateNumber": "KLM562",
			"OwnerName": "OsCAR Olofsson",
			"VehicleTypeName": "EMERGENCY"
		},
		{
			"PlateNumber": "RMJ473",
			"OwnerName": "Victor Vallén",
			"VehicleTypeName": "CAR"
		},
		{
			"PlateNumber": "QWE982",
			"OwnerName": "Jenny Järp",
			"VehicleTypeName": "FOREIGN"
		},
		{
			"PlateNumber": "TRP648",
			"OwnerName": "Stina Sörlén",
			"VehicleTypeName": "CAR"
		},
		{
			"PlateNumber": "ZXC101",
			"OwnerName": "Axel Åkesson",
			"VehicleTypeName": "MILITARY"
		},
		{
			"PlateNumber": "LPO839",
			"OwnerName": "Nina Norrström",
			"VehicleTypeName": "CAR"
		},
		{
			"PlateNumber": "GHT467",
			"OwnerName": "Felicia Forslund",
			"VehicleTypeName": "BUS"
		},
		{
			"PlateNumber": "KLB381",
			"OwnerName": "Greta Gerdman",
			"VehicleTypeName": "TRACTOR"
		},
		{
			"PlateNumber": "XOP122",
			"OwnerName": "Erik Eklund",
			"VehicleTypeName": "DIPLOMAT"
		},
		{
			"PlateNumber": "WZX771",
			"OwnerName": "Beatrice Boström",
			"VehicleTypeName": "CAR"
		},
		{
			"PlateNumber": "HUE294",
			"OwnerName": "Fredrik Friberg",
			"VehicleTypeName": "CAR"
		},
		{
			"PlateNumber": "LPD450",
			"OwnerName": "Astrid Albinsson",
			"VehicleTypeName": "CAR"
		},
		{
			"PlateNumber": "PRT999",
			"OwnerName": "Sigge Sandström",
			"VehicleTypeName": "FOREIGN"
		},
		{
			"PlateNumber": "KNL238",
			"OwnerName": "Kajsa Källström",
			"VehicleTypeName": "CAR"
		},
		{
			"PlateNumber": "UBK768",
			"OwnerName": "Torvald Tollberg",
			"VehicleTypeName": "TRUCK"
		},
		{
			"PlateNumber": "EMG482",
			"OwnerName": "Lilly Lind",
			"VehicleTypeName": "CAR"
		},
		{
			"PlateNumber": "JNH590",
			"OwnerName": "Bertil Bäckström",
			"VehicleTypeName": "CAR"
		},
		{
			"PlateNumber": "JOL342",
			"OwnerName": "Hanna Hultgren",
			"VehicleTypeName": "EMERGENCY"
		},
		{
			"PlateNumber": "WMD229",
			"OwnerName": "Dagmar Dahlen",
			"VehicleTypeName": "CAR"
		},
		{
			"PlateNumber": "TYC992",
			"OwnerName": "Oskar Odelberg",
			"VehicleTypeName": "CAR"
		},
		{
			"PlateNumber": "TRD147",
			"OwnerName": "Clara CARlsson",
			"VehicleTypeName": "MOTORCYCLE"
		},
		{
			"PlateNumber": "BXA321",
			"OwnerName": "Harry Hägglund",
			"VehicleTypeName": "MILITARY"
		},
		{
			"PlateNumber": "PLT465",
			"OwnerName": "Elsa Eklund",
			"VehicleTypeName": "CAR"
		},
		{
			"PlateNumber": "GFX109",
			"OwnerName": "Ulf Ulander",
			"VehicleTypeName": "TRUCK"
		},
		{
			"PlateNumber": "LSQ555",
			"OwnerName": "Märta Melin",
			"VehicleTypeName": "BUS"
		},
		{
			"PlateNumber": "NKI211",
			"OwnerName": "Simon Stenberg",
			"VehicleTypeName": "CAR"
		},
		{
			"PlateNumber": "FPZ830",
			"OwnerName": "Ingrid Irén",
			"VehicleTypeName": "CAR"
		},
		{
			"PlateNumber": "TXR871",
			"OwnerName": "Göran Gidlund",
			"VehicleTypeName": "MILITARY"
		},
		{
			"PlateNumber": "WQL130",
			"OwnerName": "Camilla CARlsson",
			"VehicleTypeName": "CAR"
		},
		{
			"PlateNumber": "BYH376",
			"OwnerName": "Roland Rindberg",
			"VehicleTypeName": "TRUCK"
		},
		{
			"PlateNumber": "ZCP591",
			"OwnerName": "Lina Ljungholm",
			"VehicleTypeName": "CAR"
		},
		{
			"PlateNumber": "TDA643",
			"OwnerName": "Björn Björkman",
			"VehicleTypeName": "BUS"
		},
		{
			"PlateNumber": "CBX008",
			"OwnerName": "Stella Sörensson",
			"VehicleTypeName": "CAR"
		},
		{
			"PlateNumber": "HKO483",
			"OwnerName": "Einar Engström",
			"VehicleTypeName": "CAR"
		},
		{
			"PlateNumber": "WLQ599",
			"OwnerName": "Emilia Ekberg",
			"VehicleTypeName": "CAR"
		},
		{
			"PlateNumber": "YSQ102",
			"OwnerName": "Kristian Karlsson",
			"VehicleTypeName": "TRUCK"
		},
		{
			"PlateNumber": "RGX702",
			"OwnerName": "Viola Vinge",
			"VehicleTypeName": "CAR"
		},
		{
			"PlateNumber": "MTF981",
			"OwnerName": "Torsten Törnqvist",
			"VehicleTypeName": "TRUCK"
		},
		{
			"PlateNumber": "GQV753",
			"OwnerName": "Ellinor Elm",
			"VehicleTypeName": "CAR"
		},
		{
			"PlateNumber": "HZX610",
			"OwnerName": "Sven Svahn",
			"VehicleTypeName": "TRUCK"
		}
	],

	"DefaultFee": 0,

	"TollFreeMonths": [ 7 ]

}
